alarm_clock.v
module alarm_clock (
    rst_bar, clk, h1_in, h0_in, m1_in, m0_in, load_time, load_alarm, set_alarm, stop_alarm,
    alarm, h1_out, h0_out, m1_out, m0_out, s1_out, s0_out
);
    
    input   rst_bar,    // active low reset button, set alarm time to 00:00:00, and clock time to input time, and turns alarm(sound) off
            clk,        // a clock of frequency 100Hz (10ms)
            load_time,  // when high, sets clock time to input time
            load_alarm, // when high, sets alaram time to input time
            set_alarm,  // when high, alarm rings when clock time reaches alarm time
            stop_alarm; // when high, stops the ringing alarm

    input [1:0] h1_in;  // inputs the MSB of hrs,  (0-2)
    input [3:0] h0_in;  // inofputs the LSB of hrs,  (0-9)
    input [2:0] m1_in;  // inputs the MSB  mins, (0-5)
    input [3:0] m0_in;  // inputs the LSB of mins, (0-9)

    output reg alarm;         // when high, alarm rings

    output reg [1:0] h1_out;  // outputs the MSB of hrs,  (0-2)
    output reg [3:0] h0_out;  // outputs the LSB of hrs,  (0-9)
    output reg [2:0] m1_out;  // outputs the MSB of mins, (0-5)
    output reg [3:0] m0_out;  // outputs the LSB of mins, (0-9)
    output reg [2:0] s1_out;  // outputs the MSB of secs, (0-5)
    output reg [3:0] s0_out;  // outputs the LSB of secs, (0-9)

    //  we need temperory clock time and alarm time for operations to be followed

    reg [1:0] temp_c_h1, temp_a_h1;     //  MSB of hrs of clock and alarm    (0-2)
    reg [3:0] temp_c_h0, temp_a_h0;     //  LSB of hrs of clock and alarm    (0-9)
    reg [2:0] temp_c_m1, temp_a_m1;     //  MSB of mins of clock and alarm   (0-5)
    reg [3:0] temp_c_m0, temp_a_m0;     //  LSB of mins of clock and alarm   (0-9)
    reg [2:0] temp_c_s1, temp_a_s1;     //  MSB of secs of clock             (0-5)
    reg [3:0] temp_c_s0, temp_a_s0;     //  LSB of secs of clock             (0-9)

    //  we have a clock of frequency 100 Hz but for alarm clock we need a clock of frequency 1 Hz

    reg clk_1;  //  this will work as clock of frequency 1Hz 
    integer i;  //  integer value to be iterated

    always @(posedge clk or negedge rst_bar) begin
        
        if (!rst_bar) begin         //  active low reset button
            i <= 0;                 //  both i and clk_1 to be
            clk_1 <= 1'b0;          //  set to 0, at reset
        end
        else begin
            if (i>=49) begin        //  since we have a clock of frequency 100 Hz
                i <= 0;             //  halfway is at 49, where out edge must come 
                clk_1 <= ~clk_1;    //  negedge or posedge
            end
            else i<= i+1;           //  otherwise i will be incremented, until reaches halfway
        end
    end

    //  CLOCK OPERATION

    always @(negedge clk_1 or negedge rst_bar) begin  //  we will be using negedge of clock generated
        
        if (!rst_bar) begin

            temp_c_h1 <= h1_in;     //  clock time is set to input time
            temp_c_h0 <= h0_in;
            temp_c_m1 <= m1_in;
            temp_c_m0 <= m0_in;
            temp_c_s1 <= 3'b0;      //  secs set to 00
            temp_c_s0 <= 4'b0;

            temp_a_h1 <= 2'b0;      //  alarm time set to 00:00 (hh:mm)
            temp_a_h0 <= 4'b0;
            temp_a_m1 <= 3'b0;
            temp_a_m0 <= 4'b0;            
            temp_a_s1 <= 3'b0;
            temp_a_s0 <= 4'b0;

            alarm <= 1'b0;          //  alarms if ringings sounds off
        end

        else if (load_time) begin
            temp_c_h1 <= h1_in;     //  clock time is set to input time
            temp_c_h0 <= h0_in;
            temp_c_m1 <= m1_in;
            temp_c_m0 <= m0_in;
            temp_c_s1 <= 3'b0;      //  secs set to 00
            temp_c_s0 <= 4'b0;            
        end

        else if (load_alarm) begin
            temp_a_h1 <= h1_in;     //  clock time is set to input time
            temp_a_h0 <= h0_in;
            temp_a_m1 <= m1_in;
            temp_a_m0 <= m0_in;
            temp_a_s1 <= 3'b0;      //  secs set to 00
            temp_a_s0 <= 4'b0;            
        end

        else begin
            if (temp_c_s0 >= 9) begin                                   //  is s0 = 9, then s0 = 0
                temp_c_s0 <= 0;                                         //  and s1 ges incremented
                if (temp_c_s1 >= 5) begin                               //  ss == 59, it should get to 00
                    temp_c_s1 <= 0;                                     //  and m0 gets incremented
                    if (temp_c_m0 >= 9) begin                           //  if m0 = 9, then m0 = 0
                        temp_c_m0 <= 0;                                 //  and m1 gets incremented
                        if (temp_c_m1 >= 5) begin                       //  mm == 59, it should get to 00
                            temp_c_m1 <= 0;                             //  and hh gets incremented
                            if (temp_c_h1 < 2) begin                    //  if 19 gets to 20
                                if (temp_c_h0 >= 9) begin               //  if 09 gets to 10
                                    temp_c_h0 <= 0;                     //  but shouldn't reach till 29
                                    temp_c_h1 <= temp_c_h1 + 1;
                                end
                                else temp_c_h0 <= temp_c_h0 + 1;
                            end 
                            else if (temp_c_h1 >=2) begin               //  so this is seprated
                                if (temp_c_h0 >= 3) begin               //  after hh = 23, it gets to 00
                                    temp_c_h0 <= 0;
                                    temp_c_h1 <= 0;
                                end
                                else temp_c_h0 <= temp_c_h0 + 1;
                            end
                        end
                        else temp_c_m1 <= temp_c_m1 + 1;
                    end
                    else temp_c_m0 <= temp_c_m0 + 1;
                end
                else temp_c_s1 <= temp_c_s1 + 1;
            end
            else temp_c_s0 <= temp_c_s0 + 1;
        end
    end

    //  ALARM ACTION

    //  we will be adding snooze function also
    //  if alarm is not stopped, it will ring for 1min and then ring after 10 min past alarm time that is set
    //  this will repeat three times, if stop_alarm not pressed

    reg min_1,      //  alarm will ring for one min, if stop_alarm not pressed
        min_9,      //  will wait for nine mins afterwards for stop_alarm to be pressed, if not alarm will ring again
        loop_3;     //  this process repeats three times, if stop_alarm is not pressed

    reg [7:0] num_1;    //  needs to count negedges for 1 min
    reg [9:0] num_9;    //  needs to count negedges for 9 min
    reg [1:0] num_3;    //  needs to count till 2 only or 3 max

    always @(negedge clk_1 or negedge rst_bar) begin
        
        if (!rst_bar) begin         //  alarms turns off at reset
            alarm <=  1'b0;
            min_1 <=  1'b0;
            min_9 <=  1'b0;
            loop_3 <= 1'b0;
        end

        else if (set_alarm) begin   //  when set_alarm is high and clock time matches alarm time
            if ({temp_c_h1,temp_c_h0,temp_c_m1,temp_c_m0,temp_c_s1,temp_c_s0} == 
                {temp_a_h1,temp_a_h0,temp_a_m1,temp_a_m0,temp_a_s1,temp_a_s0} ) begin
            alarm <=  1'b1;         //  alarm rings
            min_1 <=  1'b1;
            min_9 <=  1'b0;
            loop_3 <= 1'b1;
            end
        end
    end

    //  SNOOZE ACTION

    always @(negedge clk_1 or negedge rst_bar or posedge stop_alarm) begin
        
        if (!rst_bar) begin         //  alarms turns off at reset
            alarm <=  1'b0;
            min_1 = 1'b0;
            min_9 = 1'b0;
            loop_3 = 1'b0;
            num_1 = 8'b0;
            num_9 = 10'b0;
            num_3 = 2'b0;
        end

        else if (stop_alarm) begin  //  alarms turns off when stop_alarm is pressed
            alarm <=  1'b0;
            min_1 = 1'b0;
            min_9 = 1'b0;
            loop_3 = 1'b0;
            num_1 = 8'b0;
            num_9 = 10'b0;
            num_3 = 2'b0;
        end
        
        else if (loop_3 || min_1) begin
            if (min_1) begin
                alarm <= 1'b1;
            end
            else if (min_9) begin
                alarm <= 1'b0;
            end
        end

        else begin                  //  no response from user, repeating process turns off
            alarm <=  1'b0;
            min_1 = 1'b0;
            min_9 = 1'b0;
            loop_3 = 1'b0;
            num_1 = 8'b0;
            num_9 = 10'b0;
            num_3 = 2'b0;         
        end
    end

    //  COUNTING OPERATION

    always @(negedge clk_1 or negedge rst_bar) begin

        if (!rst_bar) begin         //  alarms turns off at reset
            alarm <=  1'b0;
            min_1 = 1'b0;
            min_9 = 1'b0;
            loop_3 = 1'b0;
            num_1 = 8'b0;
            num_9 = 10'b0;
            num_3 = 2'b0;
        end

        else if (loop_3) begin

            if (num_3 >= 2) begin
                num_3  <= 2'b0;
                loop_3 <= 1'b0;
            end

            else begin

                if (min_1) begin
                    if (num_1 >= 60) begin
                        num_1 <= 8'b0;
                        min_1 <= 1'b0;
                        min_9 <= 1'b1;
                    end
                    else num_1 <= num_1 + 1;
                end

                else if (min_9) begin
                    if (num_9 >= 540) begin
                        num_9 <= 10'b0;
                        min_1 <= 1'b1;
                        min_9 <= 1'b0;
                        num_3 <= num_3 + 1;
                    end
                    else num_9 <= num_9 + 1;
                end
            end
        end

        else if (min_1) begin
            if (num_1 >= 60) begin
                num_1 <= 8'b0;
                min_1 <= 1'b0;
            end
            else num_1 <= num_1 + 1;
        end

        else begin
            min_1 = 1'b0;
            min_9 = 1'b0;
            loop_3 = 1'b0;
            num_1 = 8'b0;
            num_9 = 10'b0;
            num_3 = 2'b0;
        end 
    end

    // OUTPUT

    always @(negedge clk_1 or negedge rst_bar) begin
        if (!rst_bar) begin
            h1_out <= h1_in;
            h0_out <= h0_in;
            m1_out <= m1_in;
            m0_out <= m0_in;
            s1_out <= 3'b0;
            s0_out <= 4'b0;
        end
        else begin
            h1_out <= temp_c_h1;
            h0_out <= temp_c_h0;
            m1_out <= temp_c_m1;
            m0_out <= temp_c_m0;
            s1_out <= temp_c_s1;
            s0_out <= temp_c_s0;
        end
    end

endmodule

tb_alarm_clock.v
`timescale 1ms/1ms
`include "alarm_clock.v"

module tb_alarm_clock;

    reg clk, rst_bar, load_time, load_alarm, set_alarm, stop_alarm;     //  inputs are declared reg datatype

    reg [1:0] h1_in;  // MSB of hrs,  (0-2)
    reg [3:0] h0_in;  // LSB of hrs,  (0-9)
    reg [2:0] m1_in;  // MSB of mins, (0-5)
    reg [3:0] m0_in;  // LSB of mins, (0-9)

    wire alarm;         // outputs are declared wire datatype

    wire [1:0] h1_out;  // MSB of hrs,  (0-2)
    wire [3:0] h0_out;  // LSB of hrs,  (0-9)
    wire [2:0] m1_out;  // MSB of mins, (0-5)
    wire [3:0] m0_out;  // LSB of mins, (0-9)
    wire [2:0] s1_out;  // MSB of secs, (0-5)
    wire [3:0] s0_out;  // LSB of secs, (0-9)

    //  INITIALISING THE ALARM CLOCK

    alarm_clock DUT     
    (
    rst_bar, clk, h1_in, h0_in, m1_in, m0_in, load_time, load_alarm, set_alarm, stop_alarm,
    alarm, h1_out, h0_out, m1_out, m0_out, s1_out, s0_out
    );

    localparam CLK_PERIOD = 10;             //  clock with timeperiod 10ms (100 Hz)
    always #(CLK_PERIOD/2) clk=~clk;

    initial begin
        $dumpfile("tb_alarm_clock.vcd");                                            //  file to be dumped inn, for gtkwave
        $dumpvars(1, alarm, h1_out, h0_out, m1_out, m0_out, s1_out, s0_out);        //  variables to be dumped
        $monitor($time," rst_bar = %b set_alarm = %b stop_alarm = %b input time = %d%d : %d%d output time = %d%d : %d%d alarm = %b",rst_bar,set_alarm,stop_alarm,h1_in,h0_in,m1_in,m0_in,h1_out,h0_out,m1_out,m0_out,alarm);               //  to be printed on screen
    end

    initial begin                           //  initialising at t = 0
        clk = 1'b0;
        rst_bar = 1'b0;

        h1_in = 2'd1;   h0_in = 4'd1;       //  initialised input time 11:43 (hh:mm)   
        m1_in = 3'd4;   m0_in = 4'd3;
    
        set_alarm = 1'b0;   stop_alarm = 1'b0;  
    end

    initial begin   //  handles reset button (active low)
        
        #1e3    rst_bar = 1'b1;     //  t = 1sec
        #32e6   rst_bar = 1'b0;     //  t = 32001 sec
        #1e3    rst_bar = 1'b1;     //  t = 32002 sec
        #274e4  rst_bar = 1'b0;     //  t = 34742 sec
        #1e3    rst_bar = 1'b1;     //  t = 34743 sec

    end

    initial begin   //  handles input time 
    
        #1e4    h1_in = 2'd0;   h0_in = 4'd7;       //  input time 07:10 (hh:mm) at t = 10 sec   
                m1_in = 3'd1;   m0_in = 4'd0;
        
        #4e4    h1_in = 2'd0;   h0_in = 4'd9;       //  input time 09:05 (hh:mm) at t = 50 sec   
                m1_in = 3'd0;   m0_in = 4'd5;
        
        #9e6    h1_in = 2'd1;   h0_in = 4'd2;       //  input time 12:10 (hh:mm) at t = 9050 sec   
                m1_in = 3'd1;   m0_in = 4'd0;
        
        #1e7    h1_in = 2'd1;   h0_in = 4'd3;       //  input time 13:40 (hh:mm) at t = 19050 sec   
                m1_in = 3'd4;   m0_in = 4'd0;
        
        #6e6    h1_in = 2'd1;   h0_in = 4'd5;       //  input time 15:30 (hh:mm) at t = 25050 sec   
                m1_in = 3'd3;   m0_in = 4'd0;

        #6e6    h1_in = 2'd2;   h0_in = 4'd3;       //  input time 23:15 (hh:mm) at t = 31050 sec   
                m1_in = 3'd1;   m0_in = 4'd5;       
            
    end

    initial begin                   //  handles load_time button (active high)
        
        #3e4    load_time = 1'b1;   //  t = 30 sec
        #1e3    load_time = 1'b0;   //  t = 31 sec
    
    end

    initial begin                   //  handles load_alarm button (active high)
        
        #7e4    load_alarm = 1'b1;  //  t = 70 sec
        #1e3    load_alarm = 1'b0;  //  t = 71 sec
        #9e6    load_alarm = 1'b1;  //  t = 9071 sec
        #1e3    load_alarm = 1'b0;  //  t = 9072 sec
        #1e7    load_alarm = 1'b1;  //  t = 19072 sec
        #1e3    load_alarm = 1'b0;  //  t = 19073 sec
        #6e6    load_alarm = 1'b1;  //  t = 25073 sec
        #1e3    load_alarm = 1'b0;  //  t = 25074 sec

    end


    initial begin                   //  handles set_alarm button (active high)
       
        #1e7    set_alarm = 1'b1;   // t = 10000 sec
    
    end

    initial begin                   //  handles stop_alarm button (active high)
        
        #24e6   stop_alarm = 1'b1;  //  t = 24000 sec
        #1e3    stop_alarm = 1'b0;  //  t = 24001 sec
        #6059e3 stop_alarm = 1'b1;  //  t = 30060 sec
        #1e3    stop_alarm = 1'b0;  //  t = 30061 sec

    end

    initial begin
        #35e6   $finish;            //  t = 35000 sec
    end

endmodule

tb_alarm_clock.vcd
$date
	Sat Jul 08 22:18:08 2023
$end
$version
	Icarus Verilog
$end
$timescale
	1ms
$end
$scope module tb_alarm_clock $end
$var wire 1 ! alarm $end
$upscope $end
$scope module tb_alarm_clock $end
$var wire 2 " h1_out [1:0] $end
$upscope $end
$scope module tb_alarm_clock $end
$var wire 4 # h0_out [3:0] $end
$upscope $end
$scope module tb_alarm_clock $end
$var wire 3 $ m1_out [2:0] $end
$upscope $end
$scope module tb_alarm_clock $end
$var wire 4 % m0_out [3:0] $end
$upscope $end
$scope module tb_alarm_clock $end
$var wire 3 & s1_out [2:0] $end
$upscope $end
$scope module tb_alarm_clock $end
$var wire 4 ' s0_out [3:0] $end
$upscope $end
$enddefinitions $end
$comment Show the parameter values. $end
$dumpall
$end
#0
$dumpvars
b0 '
b0 &
b11 %
b100 $
b1 #
b1 "
0!
$end
#2995
b1 '
#3995
b10 '
#4995
b11 '
#5995
b100 '
#6995
b101 '
#7995
b110 '
#8995
b111 '
#9995
b1000 '
#10995
b1001 '
#11995
b0 '
b1 &
#12995
b1 '
#13995
b10 '
#14995
b11 '
#15995
b100 '
#16995
b101 '
#17995
b110 '
#18995
b111 '
#19995
b1000 '
#20995
b1001 '
#21995
b0 '
b10 &
#22995
b1 '
#23995
b10 '
#24995
b11 '
#25995
b100 '
#26995
b101 '
#27995
b110 '
#28995
b111 '
#29995
b1000 '
#30995
b1001 '
#31995
b0 '
b0 &
b0 %
b1 $
b111 #
b0 "
#32995
b1 '
#33995
b10 '
#34995
b11 '
#35995
b100 '
#36995
b101 '
#37995
b110 '
#38995
b111 '
#39995
b1000 '
#40995
b1001 '
#41995
b0 '
b1 &
#42995
b1 '
#43995
b10 '
#44995
b11 '
#45995
b100 '
#46995
b101 '
#47995
b110 '
#48995
b111 '
#49995
b1000 '
#50995
b1001 '
#51995
b0 '
b10 &
#52995
b1 '
#53995
b10 '
#54995
b11 '
#55995
b100 '
#56995
b101 '
#57995
b110 '
#58995
b111 '
#59995
b1000 '
#60995
b1001 '
#61995
b0 '
b11 &
#62995
b1 '
#63995
b10 '
#64995
b11 '
#65995
b100 '
#66995
b101 '
#67995
b110 '
#68995
b111 '
#69995
b1000 '
#70995
b1001 '
#72995
b0 '
b100 &
#73995
b1 '
#74995
b10 '
#75995
b11 '
#76995
b100 '
#77995
b101 '
#78995
b110 '
#79995
b111 '
#80995
b1000 '
#81995
b1001 '
#82995
b0 '
b101 &
#83995
b1 '
#84995
b10 '
#85995
b11 '
#86995
b100 '
#87995
b101 '
#88995
b110 '
#89995
b111 '
#90995
b1000 '
#91995
b1001 '
#92995
b0 '
b0 &
b1 %
#93995
b1 '
#94995
b10 '
#95995
b11 '
#96995
b100 '
#97995
b101 '
#98995
b110 '
#99995
b111 '
#100995
b1000 '
#101995
b1001 '
#102995
b0 '
b1 &
#103995
b1 '
#104995
b10 '
#105995
b11 '
#106995
b100 '
#107995
b101 '
#108995
b110 '
#109995
b111 '
#110995
b1000 '
#111995
b1001 '
#112995
b0 '
b10 &
#113995
b1 '
#114995
b10 '
#115995
b11 '
#116995
b100 '
#117995
b101 '
#118995
b110 '
#119995
b111 '
#120995
b1000 '
#121995
b1001 '
#122995
b0 '
b11 &
#123995
b1 '
#124995
b10 '
#125995
b11 '
#126995
b100 '
#127995
b101 '
#128995
b110 '
#129995
b111 '
#130995
b1000 '
#131995
b1001 '
#132995
b0 '
b100 &
#133995
b1 '
#134995
b10 '
#135995
b11 '
#136995
b100 '
#137995
b101 '
#138995
b110 '
#139995
b111 '
#140995
b1000 '
#141995
b1001 '
#142995
b0 '
b101 &
#143995
b1 '
#144995
b10 '
#145995
b11 '
#146995
b100 '
#147995
b101 '
#148995
b110 '
#149995
b111 '
#150995
b1000 '
#151995
b1001 '
#152995
b0 '
b0 &
b10 %
#153995
b1 '
#154995
b10 '
#155995
b11 '
#156995
b100 '
#157995
b101 '
#158995
b110 '
#159995
b111 '
#160995
b1000 '
#161995
b1001 '
#162995
b0 '
b1 &
#163995
b1 '
#164995
b10 '
#165995
b11 '
#166995
b100 '
#167995
b101 '
#168995
b110 '
#169995
b111 '
#170995
b1000 '
#171995
b1001 '
#172995
b0 '
b10 &
#173995
b1 '
#174995
b10 '
#175995
b11 '
#176995
b100 '
#177995
b101 '
#178995
b110 '
#179995
b111 '
#180995
b1000 '
#181995
b1001 '
#182995
b0 '
b11 &
#183995
b1 '
#184995
b10 '
#185995
b11 '
#186995
b100 '
#187995
b101 '
#188995
b110 '
#189995
b111 '
#190995
b1000 '
#191995
b1001 '
#192995
b0 '
b100 &
#193995
b1 '
#194995
b10 '
#195995
b11 '
#196995
b100 '
#197995
b101 '
#198995
b110 '
#199995
b111 '
#200995
b1000 '
#201995
b1001 '
#202995
b0 '
b101 &
#203995
b1 '
#204995
b10 '
#205995
b11 '
#206995
b100 '
#207995
b101 '
#208995
b110 '
#209995
b111 '
#210995
b1000 '
#211995
b1001 '
#212995
b0 '
b0 &
b11 %
#213995
b1 '
#214995
b10 '
#215995
b11 '
#216995
b100 '
#217995
b101 '
#218995
b110 '
#219995
b111 '
#220995
b1000 '
#221995
b1001 '
#222995
b0 '
b1 &
#223995
b1 '
#224995
b10 '
#225995
b11 '
#226995
b100 '
#227995
b101 '
#228995
b110 '
#229995
b111 '
#230995
b1000 '
#231995
b1001 '
#232995
b0 '
b10 &
#233995
b1 '
#234995
b10 '
#235995
b11 '
#236995
b100 '
#237995
b101 '
#238995
b110 '
#239995
b111 '
#240995
b1000 '
#241995
b1001 '
#242995
b0 '
b11 &
#243995
b1 '
#244995
b10 '
#245995
b11 '
#246995
b100 '
#247995
b101 '
#248995
b110 '
#249995
b111 '
#250995
b1000 '
#251995
b1001 '
#252995
b0 '
b100 &
#253995
b1 '
#254995
b10 '
#255995
b11 '
#256995
b100 '
#257995
b101 '
#258995
b110 '
#259995
b111 '
#260995
b1000 '
#261995
b1001 '
#262995
b0 '
b101 &
#263995
b1 '
#264995
b10 '
#265995
b11 '
#266995
b100 '
#267995
b101 '
#268995
b110 '
#269995
b111 '
#270995
b1000 '
#271995
b1001 '
#272995
b0 '
b0 &
b100 %
#273995
b1 '
#274995
b10 '
#275995
b11 '
#276995
b100 '
#277995
b101 '
#278995
b110 '
#279995
b111 '
#280995
b1000 '
#281995
b1001 '
#282995
b0 '
b1 &
#283995
b1 '
#284995
b10 '
#285995
b11 '
#286995
b100 '
#287995
b101 '
#288995
b110 '
#289995
b111 '
#290995
b1000 '
#291995
b1001 '
#292995
b0 '
b10 &
#293995
b1 '
#294995
b10 '
#295995
b11 '
#296995
b100 '
#297995
b101 '
#298995
b110 '
#299995
b111 '
#300995
b1000 '
#301995
b1001 '
#302995
b0 '
b11 &
#303995
b1 '
#304995
b10 '
#305995
b11 '
#306995
b100 '
#307995
b101 '
#308995
b110 '
#309995
b111 '
#310995
b1000 '
#311995
b1001 '
#312995
b0 '
b100 &
#313995
b1 '
#314995
b10 '
#315995
b11 '
#316995
b100 '
#317995
b101 '
#318995
b110 '
#319995
b111 '
#320995
b1000 '
#321995
b1001 '
#322995
b0 '
b101 &
#323995
b1 '
#324995
b10 '
#325995
b11 '
#326995
b100 '
#327995
b101 '
#328995
b110 '
#329995
b111 '
#330995
b1000 '
#331995
b1001 '
#332995
b0 '
b0 &
b101 %
#333995
b1 '
#334995
b10 '
#335995
b11 '
#336995
b100 '
#337995
b101 '
#338995
b110 '
#339995
b111 '
#340995
b1000 '
#341995
b1001 '
#342995
b0 '
b1 &
#343995
b1 '
#344995
b10 '
#345995
b11 '
#346995
b100 '
#347995
b101 '
#348995
b110 '
#349995
b111 '
#350995
b1000 '
#351995
b1001 '
#352995
b0 '
b10 &
#353995
b1 '
#354995
b10 '
#355995
b11 '
#356995
b100 '
#357995
b101 '
#358995
b110 '
#359995
b111 '
#360995
b1000 '
#361995
b1001 '
#362995
b0 '
b11 &
#363995
b1 '
#364995
b10 '
#365995
b11 '
#366995
b100 '
#367995
b101 '
#368995
b110 '
#369995
b111 '
#370995
b1000 '
#371995
b1001 '
#372995
b0 '
b100 &
#373995
b1 '
#374995
b10 '
#375995
b11 '
#376995
b100 '
#377995
b101 '
#378995
b110 '
#379995
b111 '
#380995
b1000 '
#381995
b1001 '
#382995
b0 '
b101 &
#383995
b1 '
#384995
b10 '
#385995
b11 '
#386995
b100 '
#387995
b101 '
#388995
b110 '
#389995
b111 '
#390995
b1000 '
#391995
b1001 '
#392995
b0 '
b0 &
b110 %
#393995
b1 '
#394995
b10 '
#395995
b11 '
#396995
b100 '
#397995
b101 '
#398995
b110 '
#399995
b111 '
#400995
b1000 '
#401995
b1001 '
#402995
b0 '
b1 &
#403995
b1 '
#404995
b10 '
#405995
b11 '
#406995
b100 '
#407995
b101 '
#408995
b110 '
#409995
b111 '
#410995
b1000 '
#411995
b1001 '
#412995
b0 '
b10 &
#413995
b1 '
#414995
b10 '
#415995
b11 '
#416995
b100 '
#417995
b101 '
#418995
b110 '
#419995
b111 '
#420995
b1000 '
#421995
b1001 '
#422995
b0 '
b11 &
#423995
b1 '
#424995
b10 '
#425995
b11 '
#426995
b100 '
#427995
b101 '
#428995
b110 '
#429995
b111 '
#430995
b1000 '
#431995
b1001 '
#432995
b0 '
b100 &
#433995
b1 '
#434995
b10 '
#435995
b11 '
#436995
b100 '
#437995
b101 '
#438995
b110 '
#439995
b111 '
#440995
b1000 '
#441995
b1001 '
#442995
b0 '
b101 &
#443995
b1 '
#444995
b10 '
#445995
b11 '
#446995
b100 '
#447995
b101 '
#448995
b110 '
#449995
b111 '
#450995
b1000 '
#451995
b1001 '
#452995
b0 '
b0 &
b111 %
#453995
b1 '
#454995
b10 '
#455995
b11 '
#456995
b100 '
#457995
b101 '
#458995
b110 '
#459995
b111 '
#460995
b1000 '
#461995
b1001 '
#462995
b0 '
b1 &
#463995
b1 '
#464995
b10 '
#465995
b11 '
#466995
b100 '
#467995
b101 '
#468995
b110 '
#469995
b111 '
#470995
b1000 '
#471995
b1001 '
#472995
b0 '
b10 &
#473995
b1 '
#474995
b10 '
#475995
b11 '
#476995
b100 '
#477995
b101 '
#478995
b110 '
#479995
b111 '
#480995
b1000 '
#481995
b1001 '
#482995
b0 '
b11 &
#483995
b1 '
#484995
b10 '
#485995
b11 '
#486995
b100 '
#487995
b101 '
#488995
b110 '
#489995
b111 '
#490995
b1000 '
#491995
b1001 '
#492995
b0 '
b100 &
#493995
b1 '
#494995
b10 '
#495995
b11 '
#496995
b100 '
#497995
b101 '
#498995
b110 '
#499995
b111 '
#500995
b1000 '
#501995
b1001 '
#502995
b0 '
b101 &
#503995
b1 '
#504995
b10 '
#505995
b11 '
#506995
b100 '
#507995
b101 '
#508995
b110 '
#509995
b111 '
#510995
b1000 '
#511995
b1001 '
#512995
b0 '
b0 &
b1000 %
#513995
b1 '
#514995
b10 '
#515995
b11 '
#516995
b100 '
#517995
b101 '
#518995
b110 '
#519995
b111 '
#520995
b1000 '
#521995
b1001 '
#522995
b0 '
b1 &
#523995
b1 '
#524995
b10 '
#525995
b11 '
#526995
b100 '
#527995
b101 '
#528995
b110 '
#529995
b111 '
#530995
b1000 '
#531995
b1001 '
#532995
b0 '
b10 &
#533995
b1 '
#534995
b10 '
#535995
b11 '
#536995
b100 '
#537995
b101 '
#538995
b110 '
#539995
b111 '
#540995
b1000 '
#541995
b1001 '
#542995
b0 '
b11 &
#543995
b1 '
#544995
b10 '
#545995
b11 '
#546995
b100 '
#547995
b101 '
#548995
b110 '
#549995
b111 '
#550995
b1000 '
#551995
b1001 '
#552995
b0 '
b100 &
#553995
b1 '
#554995
b10 '
#555995
b11 '
#556995
b100 '
#557995
b101 '
#558995
b110 '
#559995
b111 '
#560995
b1000 '
#561995
b1001 '
#562995
b0 '
b101 &
#563995
b1 '
#564995
b10 '
#565995
b11 '
#566995
b100 '
#567995
b101 '
#568995
b110 '
#569995
b111 '
#570995
b1000 '
#571995
b1001 '
#572995
b0 '
b0 &
b1001 %
#573995
b1 '
#574995
b10 '
#575995
b11 '
#576995
b100 '
#577995
b101 '
#578995
b110 '
#579995
b111 '
#580995
b1000 '
#581995
b1001 '
#582995
b0 '
b1 &
#583995
b1 '
#584995
b10 '
#585995
b11 '
#586995
b100 '
#587995
b101 '
#588995
b110 '
#589995
b111 '
#590995
b1000 '
#591995
b1001 '
#592995
b0 '
b10 &
#593995
b1 '
#594995
b10 '
#595995
b11 '
#596995
b100 '
#597995
b101 '
#598995
b110 '
#599995
b111 '
#600995
b1000 '
#601995
b1001 '
#602995
b0 '
b11 &
#603995
b1 '
#604995
b10 '
#605995
b11 '
#606995
b100 '
#607995
b101 '
#608995
b110 '
#609995
b111 '
#610995
b1000 '
#611995
b1001 '
#612995
b0 '
b100 &
#613995
b1 '
#614995
b10 '
#615995
b11 '
#616995
b100 '
#617995
b101 '
#618995
b110 '
#619995
b111 '
#620995
b1000 '
#621995
b1001 '
#622995
b0 '
b101 &
#623995
b1 '
#624995
b10 '
#625995
b11 '
#626995
b100 '
#627995
b101 '
#628995
b110 '
#629995
b111 '
#630995
b1000 '
#631995
b1001 '
#632995
b0 '
b0 &
b0 %
b10 $
#633995
b1 '
#634995
b10 '
#635995
b11 '
#636995
b100 '
#637995
b101 '
#638995
b110 '
#639995
b111 '
#640995
b1000 '
#641995
b1001 '
#642995
b0 '
b1 &
#643995
b1 '
#644995
b10 '
#645995
b11 '
#646995
b100 '
#647995
b101 '
#648995
b110 '
#649995
b111 '
#650995
b1000 '
#651995
b1001 '
#652995
b0 '
b10 &
#653995
b1 '
#654995
b10 '
#655995
b11 '
#656995
b100 '
#657995
b101 '
#658995
b110 '
#659995
b111 '
#660995
b1000 '
#661995
b1001 '
#662995
b0 '
b11 &
#663995
b1 '
#664995
b10 '
#665995
b11 '
#666995
b100 '
#667995
b101 '
#668995
b110 '
#669995
b111 '
#670995
b1000 '
#671995
b1001 '
#672995
b0 '
b100 &
#673995
b1 '
#674995
b10 '
#675995
b11 '
#676995
b100 '
#677995
b101 '
#678995
b110 '
#679995
b111 '
#680995
b1000 '
#681995
b1001 '
#682995
b0 '
b101 &
#683995
b1 '
#684995
b10 '
#685995
b11 '
#686995
b100 '
#687995
b101 '
#688995
b110 '
#689995
b111 '
#690995
b1000 '
#691995
b1001 '
#692995
b0 '
b0 &
b1 %
#693995
b1 '
#694995
b10 '
#695995
b11 '
#696995
b100 '
#697995
b101 '
#698995
b110 '
#699995
b111 '
#700995
b1000 '
#701995
b1001 '
#702995
b0 '
b1 &
#703995
b1 '
#704995
b10 '
#705995
b11 '
#706995
b100 '
#707995
b101 '
#708995
b110 '
#709995
b111 '
#710995
b1000 '
#711995
b1001 '
#712995
b0 '
b10 &
#713995
b1 '
#714995
b10 '
#715995
b11 '
#716995
b100 '
#717995
b101 '
#718995
b110 '
#719995
b111 '
#720995
b1000 '
#721995
b1001 '
#722995
b0 '
b11 &
#723995
b1 '
#724995
b10 '
#725995
b11 '
#726995
b100 '
#727995
b101 '
#728995
b110 '
#729995
b111 '
#730995
b1000 '
#731995
b1001 '
#732995
b0 '
b100 &
#733995
b1 '
#734995
b10 '
#735995
b11 '
#736995
b100 '
#737995
b101 '
#738995
b110 '
#739995
b111 '
#740995
b1000 '
#741995
b1001 '
#742995
b0 '
b101 &
#743995
b1 '
#744995
b10 '
#745995
b11 '
#746995
b100 '
#747995
b101 '
#748995
b110 '
#749995
b111 '
#750995
b1000 '
#751995
b1001 '
#752995
b0 '
b0 &
b10 %
#753995
b1 '
#754995
b10 '
#755995
b11 '
#756995
b100 '
#757995
b101 '
#758995
b110 '
#759995
b111 '
#760995
b1000 '
#761995
b1001 '
#762995
b0 '
b1 &
#763995
b1 '
#764995
b10 '
#765995
b11 '
#766995
b100 '
#767995
b101 '
#768995
b110 '
#769995
b111 '
#770995
b1000 '
#771995
b1001 '
#772995
b0 '
b10 &
#773995
b1 '
#774995
b10 '
#775995
b11 '
#776995
b100 '
#777995
b101 '
#778995
b110 '
#779995
b111 '
#780995
b1000 '
#781995
b1001 '
#782995
b0 '
b11 &
#783995
b1 '
#784995
b10 '
#785995
b11 '
#786995
b100 '
#787995
b101 '
#788995
b110 '
#789995
b111 '
#790995
b1000 '
#791995
b1001 '
#792995
b0 '
b100 &
#793995
b1 '
#794995
b10 '
